kongcore/__init__.py
kong_ran-1.0.4.dist-info/LICENSE
kong_ran-1.0.4.dist-info/METADATA
kong_ran-1.0.4.dist-info/WHEEL
kong_ran-1.0.4.dist-info/top_level.txt
kong_ran-1.0.4.dist-info/RECORD
